odoo/addons/l10n_br_nfe_spec/README.rst
odoo/addons/l10n_br_nfe_spec/__init__.py
odoo/addons/l10n_br_nfe_spec/__manifest__.py
odoo/addons/l10n_br_nfe_spec/i18n/l10n_br_nfe_spec.pot
odoo/addons/l10n_br_nfe_spec/i18n/pt_BR.po
odoo/addons/l10n_br_nfe_spec/migrations/14.0.5.0.0/pre-migration.py
odoo/addons/l10n_br_nfe_spec/models/__init__.py
odoo/addons/l10n_br_nfe_spec/models/spec_mixin.py
odoo/addons/l10n_br_nfe_spec/models/v4_0/__init__.py
odoo/addons/l10n_br_nfe_spec/models/v4_0/leiaute_cons_sit_nfe_v4_00.py
odoo/addons/l10n_br_nfe_spec/models/v4_0/leiaute_inut_nfe_v4_00.py
odoo/addons/l10n_br_nfe_spec/models/v4_0/leiaute_nfe_v4_00.py
odoo/addons/l10n_br_nfe_spec/models/v4_0/tipos_basico_v4_00.py
odoo/addons/l10n_br_nfe_spec/readme/CONFIGURE.rst
odoo/addons/l10n_br_nfe_spec/readme/CONTRIBUTORS.rst
odoo/addons/l10n_br_nfe_spec/readme/DESCRIPTION.rst
odoo/addons/l10n_br_nfe_spec/readme/INSTALL.rst
odoo/addons/l10n_br_nfe_spec/readme/ROADMAP.rst
odoo/addons/l10n_br_nfe_spec/readme/USAGE.rst
odoo/addons/l10n_br_nfe_spec/static/description/icon.png
odoo/addons/l10n_br_nfe_spec/static/description/index.html
odoo/addons/l10n_br_nfe_spec/tests/__init__.py
odoo/addons/l10n_br_nfe_spec/tests/test_nfe_import.py
odoo14_addon_l10n_br_nfe_spec-14.0.7.0.1.dist-info/METADATA
odoo14_addon_l10n_br_nfe_spec-14.0.7.0.1.dist-info/WHEEL
odoo14_addon_l10n_br_nfe_spec-14.0.7.0.1.dist-info/top_level.txt
odoo14_addon_l10n_br_nfe_spec-14.0.7.0.1.dist-info/RECORD
